BENPPy/BayesENproteomics.py
BENPPy/__init__.py
BENPPy/benppywrapper.py
BENPPy-1.0.7.dist-info/LICENSE
BENPPy-1.0.7.dist-info/METADATA
BENPPy-1.0.7.dist-info/WHEEL
BENPPy-1.0.7.dist-info/top_level.txt
BENPPy-1.0.7.dist-info/RECORD
