Metadata-Version: 2.1
Name: BENPPy
Version: 1.0.7
Summary: BayesENproteomics in Python
Home-page: https://github.com/VenkMallikarjun/BENPPy
Author: Venkatesh Mallikarjun
Author-email: vjmallikarjun@gmail.com
License: MIT License
Keywords: proteomics PTMs MCMC
Platform: UNKNOWN
Classifier: Development Status :: 4 - Beta
Classifier: Intended Audience :: Science/Research
Classifier: License :: OSI Approved :: MIT License
Classifier: Programming Language :: Python
Classifier: Topic :: Scientific/Engineering
Classifier: Operating System :: OS Independent
Requires-Dist: pymc3
